{"success": true, "parcel": {"id": 5279, "height": 9, "token": null, "name": null, "traffic_visits": null, "address": "149 Mainnet Bypass", "visible": true, "geometry": {"type": "Polygon", "crs": {"type": "name", "properties": {"name": "EPSG:3857"}}, "coordinates": [[[-7.02, 2.599900007], [-7.02, 2.54], [-7.11, 2.54], [-7.11, 2.599900007], [-7.02, 2.599900007]]]}, "area": 53.910006650746254, "streets": [{"name": "Mainnet Bypass", "geometry": {"type": "LineString", "coordinates": [[-7, 2.28], [-7, 4.72]]}, "visible": true, "kind": null, "island": "Satoshi", "id": 2207}, {"name": "Smart Contract Crescent", "geometry": {"type": "LineString", "coordinates": [[-7, 2.58], [-6.65, 2.58]]}, "visible": true, "kind": null, "island": "Satoshi", "id": 2256}, {"name": "Fork Fork", "geometry": {"type": "LineString", "coordinates": [[-7.27, 2.52], [-7, 2.52]]}, "visible": true, "kind": null, "island": "Satoshi", "id": 2295}, {"name": "Flippening Landing", "geometry": {"type": "LineString", "coordinates": [[-7.13, 2.52], [-7.13, 2.75]]}, "visible": true, "kind": null, "island": "Satoshi", "id": 2319}], "distance": 746.5386795069629, "x1": -711, "x2": -702, "y1": 0, "y2": 9, "z1": 254, "z2": 260, "suburb": "Satoshi", "is_common": false, "owner": "0xa73dc2f955bca7f3f2d39c0926583174aa1ef0b4", "owner_name": "0xa73dc2f9...", "contributors": null, "label": null, "description": null, "sandbox": false, "lightmap_status": "None", "grid": false, "price": null, "content": {"features": []}, "island": "Satoshi", "kind": "plot"}}